graphql_error_logger/__init__.py
graphql_error_logger-0.0.3.dist-info/LICENSE
graphql_error_logger-0.0.3.dist-info/METADATA
graphql_error_logger-0.0.3.dist-info/WHEEL
graphql_error_logger-0.0.3.dist-info/top_level.txt
graphql_error_logger-0.0.3.dist-info/RECORD
